flask_css_bundler
