Metadata-Version: 2.1
Name: flask-css-bundler
Version: 1.1.1
Summary: Easy Flask CSS bundler
Author: 0x1618 aka ctrlshifti (Maksymilian Sawicz)
Author-email: <max.sawicz@gmail.com>
Keywords: python,css,flask,bundler,css bundler
